{
  "Version": 1,
  "WorkspaceRootPath": "C:\\Users\\templ\\source\\repos\\LearnRazorPages\\",
  "Documents": [
    {
      "AbsoluteMoniker": "D:0:0:{70C6693E-BF97-474E-91F4-C047AF89058D}|WebApp\\WebApp.csproj|c:\\users\\templ\\source\\repos\\learnrazorpages\\webapp\\pages\\employees\\edit.cshtml.cs||{A6C744A8-0E4A-4FC6-886A-064283054674}",
      "RelativeMoniker": "D:0:0:{70C6693E-BF97-474E-91F4-C047AF89058D}|WebApp\\WebApp.csproj|solutionrelative:webapp\\pages\\employees\\edit.cshtml.cs||{A6C744A8-0E4A-4FC6-886A-064283054674}"
    },
    {
      "AbsoluteMoniker": "D:0:0:{70C6693E-BF97-474E-91F4-C047AF89058D}|WebApp\\WebApp.csproj|c:\\users\\templ\\source\\repos\\learnrazorpages\\webapp\\pages\\employees\\edit.cshtml||{40D31677-CBC0-4297-A9EF-89D907823A98}",
      "RelativeMoniker": "D:0:0:{70C6693E-BF97-474E-91F4-C047AF89058D}|WebApp\\WebApp.csproj|solutionrelative:webapp\\pages\\employees\\edit.cshtml||{40D31677-CBC0-4297-A9EF-89D907823A98}"
    },
    {
      "AbsoluteMoniker": "D:0:0:{70C6693E-BF97-474E-91F4-C047AF89058D}|WebApp\\WebApp.csproj|c:\\users\\templ\\source\\repos\\learnrazorpages\\webapp\\pages\\employees\\add.cshtml||{40D31677-CBC0-4297-A9EF-89D907823A98}",
      "RelativeMoniker": "D:0:0:{70C6693E-BF97-474E-91F4-C047AF89058D}|WebApp\\WebApp.csproj|solutionrelative:webapp\\pages\\employees\\add.cshtml||{40D31677-CBC0-4297-A9EF-89D907823A98}"
    },
    {
      "AbsoluteMoniker": "D:0:0:{70C6693E-BF97-474E-91F4-C047AF89058D}|WebApp\\WebApp.csproj|c:\\users\\templ\\source\\repos\\learnrazorpages\\webapp\\pages\\employees\\add.cshtml.cs||{A6C744A8-0E4A-4FC6-886A-064283054674}",
      "RelativeMoniker": "D:0:0:{70C6693E-BF97-474E-91F4-C047AF89058D}|WebApp\\WebApp.csproj|solutionrelative:webapp\\pages\\employees\\add.cshtml.cs||{A6C744A8-0E4A-4FC6-886A-064283054674}"
    },
    {
      "AbsoluteMoniker": "D:0:0:{70C6693E-BF97-474E-91F4-C047AF89058D}|WebApp\\WebApp.csproj|c:\\users\\templ\\source\\repos\\learnrazorpages\\webapp\\pages\\employees\\index.cshtml||{40D31677-CBC0-4297-A9EF-89D907823A98}",
      "RelativeMoniker": "D:0:0:{70C6693E-BF97-474E-91F4-C047AF89058D}|WebApp\\WebApp.csproj|solutionrelative:webapp\\pages\\employees\\index.cshtml||{40D31677-CBC0-4297-A9EF-89D907823A98}"
    },
    {
      "AbsoluteMoniker": "D:0:0:{70C6693E-BF97-474E-91F4-C047AF89058D}|WebApp\\WebApp.csproj|c:\\users\\templ\\source\\repos\\learnrazorpages\\webapp\\pages\\index.cshtml||{40D31677-CBC0-4297-A9EF-89D907823A98}",
      "RelativeMoniker": "D:0:0:{70C6693E-BF97-474E-91F4-C047AF89058D}|WebApp\\WebApp.csproj|solutionrelative:webapp\\pages\\index.cshtml||{40D31677-CBC0-4297-A9EF-89D907823A98}"
    },
    {
      "AbsoluteMoniker": "D:0:0:{70C6693E-BF97-474E-91F4-C047AF89058D}|WebApp\\WebApp.csproj|c:\\users\\templ\\source\\repos\\learnrazorpages\\webapp\\program.cs||{A6C744A8-0E4A-4FC6-886A-064283054674}",
      "RelativeMoniker": "D:0:0:{70C6693E-BF97-474E-91F4-C047AF89058D}|WebApp\\WebApp.csproj|solutionrelative:webapp\\program.cs||{A6C744A8-0E4A-4FC6-886A-064283054674}"
    },
    {
      "AbsoluteMoniker": "D:0:0:{70C6693E-BF97-474E-91F4-C047AF89058D}|WebApp\\WebApp.csproj|c:\\users\\templ\\source\\repos\\learnrazorpages\\webapp\\pages\\index.cshtml.cs||{A6C744A8-0E4A-4FC6-886A-064283054674}",
      "RelativeMoniker": "D:0:0:{70C6693E-BF97-474E-91F4-C047AF89058D}|WebApp\\WebApp.csproj|solutionrelative:webapp\\pages\\index.cshtml.cs||{A6C744A8-0E4A-4FC6-886A-064283054674}"
    }
  ],
  "DocumentGroupContainers": [
    {
      "Orientation": 0,
      "VerticalTabListWidth": 256,
      "DocumentGroups": [
        {
          "DockedWidth": 200,
          "SelectedChildIndex": 18,
          "Children": [
            {
              "$type": "Bookmark",
              "Name": "ST:130:0:{116d2292-e37d-41cd-a077-ebacac4c8cc4}"
            },
            {
              "$type": "Bookmark",
              "Name": "ST:129:0:{1fc202d4-d401-403c-9834-5b218574bb67}"
            },
            {
              "$type": "Bookmark",
              "Name": "ST:128:0:{13b12e3e-c1b4-4539-9371-4fe9a0d523fc}"
            },
            {
              "$type": "Bookmark",
              "Name": "ST:129:0:{116d2292-e37d-41cd-a077-ebacac4c8cc4}"
            },
            {
              "$type": "Bookmark",
              "Name": "ST:130:0:{1fc202d4-d401-403c-9834-5b218574bb67}"
            },
            {
              "$type": "Bookmark",
              "Name": "ST:131:0:{1fc202d4-d401-403c-9834-5b218574bb67}"
            },
            {
              "$type": "Bookmark",
              "Name": "ST:132:0:{1fc202d4-d401-403c-9834-5b218574bb67}"
            },
            {
              "$type": "Bookmark",
              "Name": "ST:133:0:{1fc202d4-d401-403c-9834-5b218574bb67}"
            },
            {
              "$type": "Bookmark",
              "Name": "ST:134:0:{1fc202d4-d401-403c-9834-5b218574bb67}"
            },
            {
              "$type": "Bookmark",
              "Name": "ST:135:0:{1fc202d4-d401-403c-9834-5b218574bb67}"
            },
            {
              "$type": "Bookmark",
              "Name": "ST:136:0:{1fc202d4-d401-403c-9834-5b218574bb67}"
            },
            {
              "$type": "Bookmark",
              "Name": "ST:137:0:{1fc202d4-d401-403c-9834-5b218574bb67}"
            },
            {
              "$type": "Bookmark",
              "Name": "ST:138:0:{1fc202d4-d401-403c-9834-5b218574bb67}"
            },
            {
              "$type": "Bookmark",
              "Name": "ST:139:0:{1fc202d4-d401-403c-9834-5b218574bb67}"
            },
            {
              "$type": "Bookmark",
              "Name": "ST:140:0:{1fc202d4-d401-403c-9834-5b218574bb67}"
            },
            {
              "$type": "Bookmark",
              "Name": "ST:141:0:{1fc202d4-d401-403c-9834-5b218574bb67}"
            },
            {
              "$type": "Bookmark",
              "Name": "ST:142:0:{1fc202d4-d401-403c-9834-5b218574bb67}"
            },
            {
              "$type": "Bookmark",
              "Name": "ST:143:0:{1fc202d4-d401-403c-9834-5b218574bb67}"
            },
            {
              "$type": "Document",
              "DocumentIndex": 0,
              "Title": "Edit.cshtml.cs",
              "DocumentMoniker": "C:\\Users\\templ\\source\\repos\\LearnRazorPages\\WebApp\\Pages\\Employees\\Edit.cshtml.cs",
              "RelativeDocumentMoniker": "WebApp\\Pages\\Employees\\Edit.cshtml.cs",
              "ToolTip": "C:\\Users\\templ\\source\\repos\\LearnRazorPages\\WebApp\\Pages\\Employees\\Edit.cshtml.cs",
              "RelativeToolTip": "WebApp\\Pages\\Employees\\Edit.cshtml.cs",
              "ViewState": "AgIAAAIAAAAAAAAAAAAIwA0AAAAAAAAAAAAAAA==",
              "Icon": "ae27a6b0-e345-4288-96df-5eaf394ee369.000738|",
              "WhenOpened": "2024-12-09T19:27:07.665Z",
              "EditorCaption": ""
            },
            {
              "$type": "Document",
              "DocumentIndex": 3,
              "Title": "Add.cshtml.cs",
              "DocumentMoniker": "C:\\Users\\templ\\source\\repos\\LearnRazorPages\\WebApp\\Pages\\Employees\\Add.cshtml.cs",
              "RelativeDocumentMoniker": "WebApp\\Pages\\Employees\\Add.cshtml.cs",
              "ToolTip": "C:\\Users\\templ\\source\\repos\\LearnRazorPages\\WebApp\\Pages\\Employees\\Add.cshtml.cs",
              "RelativeToolTip": "WebApp\\Pages\\Employees\\Add.cshtml.cs",
              "ViewState": "AgIAAAAAAAAAAAAAAAAAAAcAAAAbAAAAAAAAAA==",
              "Icon": "ae27a6b0-e345-4288-96df-5eaf394ee369.000738|",
              "WhenOpened": "2024-12-06T23:49:19.234Z"
            },
            {
              "$type": "Document",
              "DocumentIndex": 2,
              "Title": "Add.cshtml",
              "DocumentMoniker": "C:\\Users\\templ\\source\\repos\\LearnRazorPages\\WebApp\\Pages\\Employees\\Add.cshtml",
              "RelativeDocumentMoniker": "WebApp\\Pages\\Employees\\Add.cshtml",
              "ToolTip": "C:\\Users\\templ\\source\\repos\\LearnRazorPages\\WebApp\\Pages\\Employees\\Add.cshtml",
              "RelativeToolTip": "WebApp\\Pages\\Employees\\Add.cshtml",
              "ViewState": "AgIAAAAAAAAAAAAAAAAAAAAAAAAGAAAAAAAAAA==",
              "Icon": "ae27a6b0-e345-4288-96df-5eaf394ee369.000759|",
              "WhenOpened": "2024-12-06T23:39:25.967Z"
            },
            {
              "$type": "Document",
              "DocumentIndex": 4,
              "Title": "Index.cshtml",
              "DocumentMoniker": "C:\\Users\\templ\\source\\repos\\LearnRazorPages\\WebApp\\Pages\\Employees\\Index.cshtml",
              "RelativeDocumentMoniker": "WebApp\\Pages\\Employees\\Index.cshtml",
              "ToolTip": "C:\\Users\\templ\\source\\repos\\LearnRazorPages\\WebApp\\Pages\\Employees\\Index.cshtml",
              "RelativeToolTip": "WebApp\\Pages\\Employees\\Index.cshtml",
              "ViewState": "AgIAAAAAAAAAAAAAAAAAAAYAAAAAAAAAAAAAAA==",
              "Icon": "ae27a6b0-e345-4288-96df-5eaf394ee369.000759|",
              "WhenOpened": "2024-12-06T23:36:22.814Z"
            },
            {
              "$type": "Document",
              "DocumentIndex": 1,
              "Title": "Edit.cshtml",
              "DocumentMoniker": "C:\\Users\\templ\\source\\repos\\LearnRazorPages\\WebApp\\Pages\\Employees\\Edit.cshtml",
              "RelativeDocumentMoniker": "WebApp\\Pages\\Employees\\Edit.cshtml",
              "ToolTip": "C:\\Users\\templ\\source\\repos\\LearnRazorPages\\WebApp\\Pages\\Employees\\Edit.cshtml",
              "RelativeToolTip": "WebApp\\Pages\\Employees\\Edit.cshtml",
              "ViewState": "AgIAAAAAAAAAAAAAAAAAABEAAAABAAAAAAAAAA==",
              "Icon": "ae27a6b0-e345-4288-96df-5eaf394ee369.000759|",
              "WhenOpened": "2024-12-06T22:59:21.619Z",
              "EditorCaption": ""
            },
            {
              "$type": "Document",
              "DocumentIndex": 7,
              "Title": "Index.cshtml.cs",
              "DocumentMoniker": "C:\\Users\\templ\\source\\repos\\LearnRazorPages\\WebApp\\Pages\\Index.cshtml.cs",
              "RelativeDocumentMoniker": "WebApp\\Pages\\Index.cshtml.cs",
              "ToolTip": "C:\\Users\\templ\\source\\repos\\LearnRazorPages\\WebApp\\Pages\\Index.cshtml.cs",
              "RelativeToolTip": "WebApp\\Pages\\Index.cshtml.cs",
              "ViewState": "AgIAAAAAAAAAAAAAAAAAAAUAAAAnAAAAAAAAAA==",
              "Icon": "ae27a6b0-e345-4288-96df-5eaf394ee369.000738|",
              "WhenOpened": "2024-12-06T22:52:23.966Z"
            },
            {
              "$type": "Document",
              "DocumentIndex": 5,
              "Title": "Index.cshtml",
              "DocumentMoniker": "C:\\Users\\templ\\source\\repos\\LearnRazorPages\\WebApp\\Pages\\Index.cshtml",
              "RelativeDocumentMoniker": "WebApp\\Pages\\Index.cshtml",
              "ToolTip": "C:\\Users\\templ\\source\\repos\\LearnRazorPages\\WebApp\\Pages\\Index.cshtml",
              "RelativeToolTip": "WebApp\\Pages\\Index.cshtml",
              "ViewState": "AgIAAAAAAAAAAAAAAAAAAAUAAAAAAAAAAAAAAA==",
              "Icon": "ae27a6b0-e345-4288-96df-5eaf394ee369.000759|",
              "WhenOpened": "2024-12-06T22:50:56.504Z"
            },
            {
              "$type": "Document",
              "DocumentIndex": 6,
              "Title": "Program.cs",
              "DocumentMoniker": "C:\\Users\\templ\\source\\repos\\LearnRazorPages\\WebApp\\Program.cs",
              "RelativeDocumentMoniker": "WebApp\\Program.cs",
              "ToolTip": "C:\\Users\\templ\\source\\repos\\LearnRazorPages\\WebApp\\Program.cs",
              "RelativeToolTip": "WebApp\\Program.cs",
              "ViewState": "AgIAAAAAAAAAAAAAAAAAAA4AAAAAAAAAAAAAAA==",
              "Icon": "ae27a6b0-e345-4288-96df-5eaf394ee369.000738|",
              "WhenOpened": "2024-12-06T22:48:24.025Z"
            }
          ]
        }
      ]
    }
  ]
}